{
"Dict": "Dict1",
"Date": "1392/04/31",
"Quantity_Type": "مبلغ تراکنش",

"alborzAVG": "1290027635",
"alborzTotal": "7740165808",
"savojbolagh": 	 "2196323300" ,
"": 	 "3405650" ,
"fardis": 	 "10000" ,
"taleghan": 	 "574806" ,
"karaj": 	 "4240550252" ,
"nazarabad": 	 "1299301800" ,

"ardabilAVG": "1511804266",
"ardabilTotal": "9070825599",
"sarein": 	 "218120151" ,
"meshginshahr": 	 "1382967117" ,
"bilesavar": 	 "30000" ,
"ardebil": 	 "2580198331" ,
"namin": 	 "4888787000" ,
"germi": 	 "723000" ,

"azerbaijan-eastAVG": "4225497369",
"azerbaijan-eastTotal": "63382460536",
"bonab": 	 "156044430" ,
"": 	 "1045000" ,
"haris": 	 "5264000" ,
"khoda-afarin": 	 "10000" ,
"tabriz": 	 "61793616556" ,
"marand": 	 "731616000" ,
"mianeh": 	 "211353000" ,
"jolfa": 	 "1280000" ,
"bostanabad": 	 "460352250" ,
"ajabshir": 	 "830000" ,
"shabestar": 	 "4090000" ,
"ahar": 	 "6150200" ,
"malekan": 	 "1689000" ,
"maragheh": 	 "9109100" ,
"azarshahr": 	 "11000" ,

"azerbaijan-westAVG": "73528778",
"azerbaijan-westTotal": "808816556",
"salmas": 	 "23024000" ,
"bookan": 	 "45615726" ,
"sardasht": 	 "300000" ,
"miandoab": 	 "25000010" ,
"urumieh": 	 "349504000" ,
"khoy": 	 "13281900" ,
"chaypareh": 	 "1500000" ,
"piranshahr": 	 "25988420" ,
"oshnavieh": 	 "1518000" ,
"naghadeh": 	 "323067500" ,
"": 	 "17000" ,

"bushehrAVG": "235421740",
"bushehrTotal": "2118795663",
"jam": 	 "2523000" ,
"deyr": 	 "12605344" ,
"dashti": 	 "20000" ,
"boshehr": 	 "1809129340" ,
"ganaveh": 	 "14144140" ,
"kangan": 	 "23754000" ,
"tangestan": 	 "5986000" ,
"deylam": 	 "182250000" ,
"dashtestan": 	 "68383839" ,

"chahar-mahaal-bakhtiariAVG": "36813477",
"chahar-mahaal-bakhtiariTotal": "110440430",
"farsan": 	 "12745000" ,
"lordegan": 	 "521200" ,
"shahrekord": 	 "97174230" ,

"farsAVG": "1419869302",
"farsTotal": "36916601861",
"sepidan": 	 "506420120" ,
"fasa": 	 "1647059090" ,
"arsanjan": 	 "15953000" ,
"lamerd": 	 "146580130" ,
"jahrom": 	 "697634421" ,
"mamasani": 	 "273820795" ,
"estahban": 	 "200000" ,
"qir-va-karzin": 	 "5360000" ,
"gerash": 	 "436023718" ,
"darab": 	 "50338000" ,
"khorameh": 	 "43481000" ,
"": 	 "30935000" ,
"kazeroon": 	 "120457850" ,
"mehr": 	 "14007000" ,
"sarvestan": 	 "86233000" ,
"neyriz": 	 "8331500" ,
"abadeh": 	 "31765000" ,
"khorrambid": 	 "1671087000" ,
"marvdasht": 	 "579596000" ,
"firoozabad": 	 "3944100" ,
"larestan": 	 "170875350" ,
"kovar": 	 "68905830" ,
"rostam": 	 "25883000" ,
"eghlid": 	 "1282600" ,
"zarrin-dasht": 	 "18001000" ,
"shiraz": 	 "30262427357" ,

"gilanAVG": "371207703",
"gilanTotal": "5939323252",
"amlash": 	 "46255799" ,
"somesara": 	 "13450000" ,
"roodbar": 	 "52706000" ,
"talesh": 	 "9538000" ,
"fooman": 	 "9500000" ,
"masal": 	 "250000" ,
"langerood": 	 "5873450" ,
"astanehashrafieh": 	 "3447800" ,
"astara": 	 "4310000" ,
"rasht": 	 "5123613605" ,
"shaft": 	 "700000" ,
"": 	 "5500" ,
"lahijan": 	 "535009180" ,
"rodsar": 	 "25874600" ,
"siahkal": 	 "32043700" ,
"bandaranzali": 	 "76745618" ,

"golestanAVG": "320399056",
"golestanTotal": "3203990563",
"galikesh": 	 "5000" ,
"bandargaz": 	 "901812721" ,
"torkaman": 	 "32066800" ,
"aliabad": 	 "156296000" ,
"ramyan": 	 "19570000" ,
"aghghola": 	 "10000" ,
"gorgan": 	 "1865424550" ,
"kordkooy": 	 "18866382" ,
"azadshahr": 	 "12322000" ,
"gonbadkavoos": 	 "197617110" ,

"hamadanAVG": "133385610",
"hamadanTotal": "1067084884",
"hamedan": 	 "330556984" ,
"famenin": 	 "5000" ,
"razan": 	 "1400000" ,
"nahavand": 	 "10000" ,
"asadabad": 	 "1010050" ,
"tooyserkan": 	 "36016150" ,
"": 	 "700000" ,
"malayer": 	 "697386700" ,

"hormozganAVG": "166858883",
"hormozganTotal": "1168012182",
"minab": 	 "109318359" ,
"gheshm": 	 "51494550" ,
"parsian": 	 "190268123" ,
"bandarabas": 	 "191408920" ,
"bastak": 	 "150240900" ,
"": 	 "5000" ,
"bandarlengeh": 	 "475276330" ,

"ilamAVG": "593148252",
"ilamTotal": "2372593010",
"ilam": 	 "2304657010" ,
"darrehshahr": 	 "60590000" ,
"badreh": 	 "10000" ,
"dehloran": 	 "7336000" ,

"isfahanAVG": "1081418479",
"isfahanTotal": "23791206539",
"falavarjan": 	 "5640000" ,
"isfahan": 	 "18332632758" ,
"golpayegan": 	 "25128589" ,
"lenjan": 	 "201798740" ,
"najafabad": 	 "253631836" ,
"khur-va-biabanak": 	 "17682321" ,
"borkhar": 	 "39096000" ,
"naeen": 	 "13221000" ,
"tiran-va-karvan": 	 "38295000" ,
"aranbidgol": 	 "185003720" ,
"": 	 "1834491160" ,
"samirom": 	 "1601000" ,
"khansar": 	 "2041240" ,
"khomeinishahr": 	 "836270000" ,
"fereidoonshahr": 	 "1498995137" ,
"mobarakeh": 	 "1495000" ,
"shahin-shahr-va-meymeh": 	 "198273304" ,
"faridan": 	 "5035000" ,
"ardestan": 	 "63355100" ,
"natanz": 	 "4150000" ,
"shahreza": 	 "40091999" ,
"kashan": 	 "193277635" ,

"kermanAVG": "861079880",
"kermanTotal": "7749718918",
"kerman": 	 "7119307280" ,
"jiroft": 	 "350000" ,
"zarand": 	 "38969482" ,
"": 	 "5000" ,
"anar": 	 "40435830" ,
"shahrebabak": 	 "269915839" ,
"bam": 	 "96697219" ,
"sirjan": 	 "78345000" ,
"rafsanjan": 	 "105693268" ,

"kermanshahAVG": "247337120",
"kermanshahTotal": "1236685600",
"songhor": 	 "1410000" ,
"gilangharb": 	 "1300000" ,
"": 	 "41550000" ,
"kermanshah": 	 "900664600" ,
"paveh": 	 "291761000" ,

"khorasan-northAVG": "24200250",
"khorasan-northTotal": "72600750",
"bojnoord": 	 "63689750" ,
"esfarayen": 	 "8901000" ,
"shirvan": 	 "10000" ,

"khorasan-razaviAVG": "1324371736",
"khorasan-razaviTotal": "19865576045",
"ghoochan": 	 "977280" ,
"gonabad": 	 "407192889" ,
"fariman": 	 "173892000" ,
"mahvelat": 	 "2467134000" ,
"bardeskan": 	 "13000" ,
"daregaz": 	 "32900000" ,
"mashhad": 	 "12271622495" ,
"taibad": 	 "338754000" ,
"binalud": 	 "47263500" ,
"chenaran": 	 "57912500" ,
"sabzevar": 	 "147387582" ,
"kashmar": 	 "743209087" ,
"": 	 "42243876" ,
"torbatheydariyeh": 	 "10213600" ,
"neyshaboor": 	 "3124860236" ,

"khorasan-southAVG": "271732569",
"khorasan-southTotal": "1630395414",
"qaenat": 	 "1343650000" ,
"tabas": 	 "1525000" ,
"darmian": 	 "47030000" ,
"ferdos": 	 "36471764" ,
"birjand": 	 "191639650" ,
"boshrooyeh": 	 "10079000" ,

"khuzestanAVG": "187803041",
"khuzestanTotal": "3004848651",
"ahvaz": 	 "1665755480" ,
"ramshir": 	 "12400000" ,
"izeh": 	 "44055000" ,
"dasht-e-azadegan": 	 "3130000" ,
"omidieh": 	 "47532000" ,
"shoosh": 	 "10000" ,
"dezfool": 	 "552093322" ,
"behbahan": 	 "67318977" ,
"bandarmahshahr": 	 "157761756" ,
"andika": 	 "13472600" ,
"shooshtar": 	 "95914935" ,
"abadan": 	 "278304520" ,
"ramhormoz": 	 "29622011" ,
"andimeshk": 	 "1203900" ,
"bavi": 	 "35101150" ,
"masjedsoleiman": 	 "1173000" ,

"kohgiluyeh-boyer-ahmadAVG": "15020700",
"kohgiluyeh-boyer-ahmadTotal": "75103500",
"gachsaran": 	 "7708500" ,
"kohgiluyeh": 	 "53275000" ,
"boyer-ahmad": 	 "13810000" ,
"basht": 	 "90000" ,
"dana": 	 "220000" ,

"kurdistanAVG": "229110472",
"kurdistanTotal": "1374662829",
"dehgolan": 	 "6240000" ,
"marivan": 	 "72853000" ,
"saghez": 	 "237101000" ,
"baneh": 	 "126367303" ,
"sanandaj": 	 "800777526" ,
"bijar": 	 "131324000" ,

"lorestanAVG": "100147617",
"lorestanTotal": "600885700",
"boroojerd": 	 "339749300" ,
"khoramabad": 	 "98971500" ,
"aligoodarz": 	 "64445000" ,
"koohdasht": 	 "73545650" ,
"": 	 "3620000" ,
"azna": 	 "20554250" ,

"markaziAVG": "120396489",
"markaziTotal": "842775420",
"zarandieh": 	 "5006840" ,
"saveh": 	 "16184998" ,
"delijan": 	 "7959800" ,
"khomein": 	 "6194000" ,
"arak": 	 "523510800" ,
"mahallat": 	 "283518982" ,
"tafresh": 	 "400000" ,

"mazandaranAVG": "814907505",
"mazandaranTotal": "13853427593",
"chaloos": 	 "62318000" ,
"abbasabad": 	 "98194139" ,
"ghaemshahr": 	 "1915610757" ,
"amol": 	 "452951411" ,
"neka": 	 "1016129952" ,
"ramsar": 	 "74768900" ,
"noor": 	 "9063000" ,
"babolsar": 	 "243733500" ,
"sari": 	 "1992351787" ,
"savadkuh": 	 "1689515702" ,
"galoogah": 	 "129360000" ,
"fereidoonkenar": 	 "5000" ,
"": 	 "27045200" ,
"tonekabon": 	 "116348096" ,
"noshahr": 	 "5540000" ,
"behshahr": 	 "1649582155" ,
"babol": 	 "4370909994" ,

"qazvinAVG": "673227672",
"qazvinTotal": "2692910688",
"booeenzahra": 	 "102266503" ,
"takestan": 	 "1375965" ,
"alborz": 	 "27953345" ,
"qazvin": 	 "2561314875" ,

"qomAVG": "4210705730",
"qomTotal": "8421411461",
"qom": 	 "8239630461" ,
"": 	 "181781000" ,

"semnanAVG": "106516395",
"semnanTotal": "426065579",
"garmsar": 	 "8895100" ,
"semnan": 	 "367328876" ,
"shahrood": 	 "47439603" ,
"damghan": 	 "2402000" ,

"sistan-baluchestanAVG": "84253644",
"sistan-baluchestanTotal": "589775505",
"zabol": 	 "12080000" ,
"iranshahr": 	 "5000" ,
"chabahar": 	 "411106000" ,
"saravan": 	 "2420100" ,
"konarak": 	 "2733635" ,
"zahedan": 	 "161405770" ,
"": 	 "25000" ,

"tehranAVG": "126817079428",
"tehranTotal": "1902256191425",
"ghods": 	 "486294662" ,
"": 	 "920603540" ,
"firoozkooh": 	 "14999000" ,
"rey": 	 "98199500" ,
"shahryar": 	 "1926285355" ,
"eslamshahr": 	 "504399115" ,
"pishva": 	 "188050710" ,
"pakdasht": 	 "30905500" ,
"varamin": 	 "336758150" ,
"robatkarim": 	 "208434993" ,
"baharestan": 	 "26225001" ,
"tehran": 	 "1897459396449" ,
"pardis": 	 "5000" ,
"damavand": 	 "20716000" ,
"gharchak": 	 "34918450" ,

"yazdAVG": "603207701",
"yazdTotal": "3619246206",
"meibod": 	 "256660792" ,
"behabad": 	 "58819002" ,
"abarkooh": 	 "525000" ,
"ardakan": 	 "15149750" ,
"bafgh": 	 "6652620" ,
"yazd": 	 "3281439042" ,

"zanjanAVG": "717194708",
"zanjanTotal": "2868778834",
"zanjan": 	 "2706820029" ,
"abhar": 	 "180900" ,
"khoramdareh": 	 "161687905" ,
"": 	 "90000" 
}
