{
"Dict": "Dict1",
"Date": "1392/10/30",
"Quantity_Type": "تعداد پایانه دارای تراکنش",

"alborzAVG": "16443",
"alborzTotal": "115102",
"savojbolagh": 	 "4974",
"": 	 "4588",
"nazarabad": 	 "3296",
"fardis": 	 "484",
"eshtehard": 	 "2753",
"taleghan": 	 "319",
"karaj": 	 "98688",

"ardabilAVG": "4516",
"ardabilTotal": "49672",
"parsabad": 	 "11137",
"kowsar": 	 "323",
"namin": 	 "789",
"germi": 	 "1476",
"nayer": 	 "358",
"sarein": 	 "678",
"": 	 "1449",
"meshginshahr": 	 "2958",
"bilesavar": 	 "1058",
"khalkhal": 	 "2851",
"ardebil": 	 "26595",

"azerbaijan-eastAVG": "5664",
"azerbaijan-eastTotal": "124610",
"": 	 "3810",
"bonab": 	 "3442",
"charuymaq": 	 "231",
"haris": 	 "515",
"khoda-afarin": 	 "77",
"sarab": 	 "2290",
"malekan": 	 "1916",
"maragheh": 	 "6794",
"hashtrood": 	 "990",
"azarshahr": 	 "2764",
"varzaghan": 	 "400",
"tabriz": 	 "79584",
"kaleibar": 	 "696",
"marand": 	 "5318",
"mianeh": 	 "3863",
"jolfa": 	 "1969",
"bostanabad": 	 "1270",
"oskoo": 	 "1800",
"ajabshir": 	 "1055",
"shabestar": 	 "3097",
"horand": 	 "74",
"ahar": 	 "2655",

"azerbaijan-westAVG": "4500",
"azerbaijan-westTotal": "80996",
"poldasht": 	 "482",
"mahabad": 	 "7194",
"salmas": 	 "3962",
"piranshahr": 	 "3163",
"oshnavieh": 	 "1107",
"shahindezh": 	 "1542",
"naghadeh": 	 "2996",
"": 	 "1273",
"bookan": 	 "4826",
"sardasht": 	 "2029",
"makoo": 	 "2695",
"miandoab": 	 "5093",
"chaldoran": 	 "300",
"takab": 	 "1402",
"urumieh": 	 "33824",
"shoot": 	 "832",
"khoy": 	 "7386",
"chaypareh": 	 "890",

"bushehrAVG": "3426",
"bushehrTotal": "37687",
"asaloyeh": 	 "1301",
"jam": 	 "1494",
"": 	 "988",
"deyr": 	 "1240",
"tangestan": 	 "929",
"deylam": 	 "1373",
"dashtestan": 	 "5678",
"dashti": 	 "1556",
"boshehr": 	 "14089",
"ganaveh": 	 "4303",
"kangan": 	 "4736",

"chahar-mahaal-bakhtiariAVG": "2955",
"chahar-mahaal-bakhtiariTotal": "29549",
"farsan": 	 "2671",
"lordegan": 	 "2467",
"saman": 	 "1138",
"kuhrang": 	 "76",
"ardal": 	 "569",
"": 	 "923",
"bon": 	 "409",
"boroojen": 	 "5205",
"kiar": 	 "760",
"shahrekord": 	 "15331",

"farsAVG": "5121",
"farsTotal": "153620",
"sepidan": 	 "898",
"fasa": 	 "3772",
"firoozabad": 	 "2918",
"larestan": 	 "5808",
"kovar": 	 "1372",
"rostam": 	 "134",
"eghlid": 	 "2590",
"zarrin-dasht": 	 "558",
"shiraz": 	 "80794",
"arsanjan": 	 "993",
"lamerd": 	 "3515",
"jahrom": 	 "6119",
"mamasani": 	 "2503",
"estahban": 	 "1294",
"qir-va-karzin": 	 "1195",
"gerash": 	 "1218",
"darab": 	 "3683",
"khorameh": 	 "1020",
"bovanat": 	 "744",
"": 	 "3708",
"farashband": 	 "852",
"kazeroon": 	 "7163",
"mehr": 	 "1085",
"sarvestan": 	 "550",
"pasargad": 	 "644",
"khonj": 	 "924",
"neyriz": 	 "2286",
"abadeh": 	 "3642",
"khorrambid": 	 "2540",
"marvdasht": 	 "9098",

"gilanAVG": "4648",
"gilanTotal": "79015",
"amlash": 	 "784",
"shaft": 	 "714",
"": 	 "1988",
"lahijan": 	 "6138",
"siahkal": 	 "827",
"rodsar": 	 "3835",
"bandaranzali": 	 "5834",
"somesara": 	 "2830",
"roodbar": 	 "2470",
"rezvanshahr": 	 "1455",
"talesh": 	 "3388",
"fooman": 	 "1840",
"masal": 	 "1182",
"langerood": 	 "4325",
"astanehashrafieh": 	 "2792",
"astara": 	 "4912",
"rasht": 	 "33701",

"golestanAVG": "3758",
"golestanTotal": "56375",
"galikesh": 	 "1106",
"": 	 "2996",
"bandargaz": 	 "1208",
"torkaman": 	 "2499",
"gonbadkavoos": 	 "8531",
"minoodasht": 	 "1968",
"kolaleh": 	 "2272",
"maraveh-tappeh": 	 "208",
"aliabad": 	 "3684",
"ramyan": 	 "924",
"aghghola": 	 "2303",
"gorgan": 	 "21245",
"kordkooy": 	 "2118",
"gomishan": 	 "403",
"azadshahr": 	 "4910",

"hamadanAVG": "4612",
"hamadanTotal": "46120",
"hamedan": 	 "25320",
"famenin": 	 "1037",
"": 	 "1234",
"kabodarahang": 	 "1989",
"malayer": 	 "6059",
"bahar": 	 "1818",
"razan": 	 "2091",
"nahavand": 	 "3163",
"asadabad": 	 "1784",
"tooyserkan": 	 "1625",

"hormozganAVG": "4975",
"hormozganTotal": "69651",
"minab": 	 "4974",
"gheshm": 	 "13755",
"sirik": 	 "604",
"parsian": 	 "1598",
"bandarlengeh": 	 "10580",
"khomeyr": 	 "883",
"jask": 	 "727",
"rudan": 	 "1335",
"bandarabas": 	 "28750",
"bastak": 	 "2862",
"hajiabad": 	 "1070",
"bashagard": 	 "49",
"": 	 "2439",
"aboomoosa": 	 "25",

"ilamAVG": "1846",
"ilamTotal": "18455",
"ilam": 	 "10371",
"": 	 "834",
"mehran": 	 "554",
"malekshahi": 	 "241",
"abdanan": 	 "1218",
"darrehshahr": 	 "1463",
"ivan": 	 "858",
"chardavol": 	 "988",
"badreh": 	 "364",
"dehloran": 	 "1564",

"isfahanAVG": "9494",
"isfahanTotal": "227849",
"dehaghan": 	 "604",
"falavarjan": 	 "6417",
"isfahan": 	 "128497",
"mobarakeh": 	 "4894",
"fereidoonshahr": 	 "836",
"shahin-shahr-va-meymeh": 	 "7943",
"faridan": 	 "1755",
"ardestan": 	 "1749",
"natanz": 	 "1595",
"shahreza": 	 "7018",
"kashan": 	 "14442",
"golpayegan": 	 "6189",
"lenjan": 	 "8872",
"chadegan": 	 "490",
"najafabad": 	 "11076",
"khur-va-biabanak": 	 "535",
"borkhar": 	 "2582",
"naeen": 	 "1482",
"tiran-va-karvan": 	 "1742",
"aranbidgol": 	 "2419",
"": 	 "5166",
"samirom": 	 "1780",
"khansar": 	 "1246",
"khomeinishahr": 	 "8520",

"kermanAVG": "3783",
"kermanTotal": "90788",
"kerman": 	 "39406",
"rabor": 	 "315",
"faryab": 	 "101",
"rigan": 	 "172",
"kahnooj": 	 "2255",
"jiroft": 	 "4675",
"zarand": 	 "3985",
"": 	 "2888",
"rudbar-e-jonub": 	 "616",
"rafsanjan": 	 "11925",
"baft": 	 "1709",
"fahraj": 	 "165",
"orzooeeyeh": 	 "205",
"narmashir": 	 "276",
"anar": 	 "1165",
"shahrebabak": 	 "2196",
"ghaleganj": 	 "468",
"bam": 	 "4853",
"bardsir": 	 "950",
"anbarabad": 	 "720",
"sirjan": 	 "9509",
"manoojan": 	 "863",
"ravar": 	 "814",
"koohbanan": 	 "557",

"kermanshahAVG": "3097",
"kermanshahTotal": "46450",
"sarpolzahab": 	 "1436",
"salas-e-babajani": 	 "225",
"dalahu": 	 "274",
"songhor": 	 "1328",
"ravansar": 	 "1064",
"kangavar": 	 "1582",
"paveh": 	 "1943",
"hersin": 	 "1063",
"sahneh": 	 "999",
"ghasreshirin": 	 "377",
"javanrood": 	 "2932",
"eslamabadgharb": 	 "2181",
"gilangharb": 	 "624",
"": 	 "1403",
"kermanshah": 	 "29019",

"khorasan-northAVG": "2554",
"khorasan-northTotal": "20432",
"shirvan": 	 "2956",
"farooj": 	 "728",
"bojnoord": 	 "10135",
"": 	 "979",
"esfarayen": 	 "2909",
"garmeh": 	 "597",
"maneh-va-samalqan": 	 "1396",
"jajarm": 	 "732",

"khorasan-razaviAVG": "7045",
"khorasan-razaviTotal": "204296",
"ghoochan": 	 "3582",
"gonabad": 	 "2733",
"khalilabad": 	 "1173",
"fariman": 	 "1482",
"kashmar": 	 "4122",
"": 	 "7512",
"torbatheydariyeh": 	 "6010",
"bejestan": 	 "525",
"torbatjam": 	 "2854",
"sarakhs": 	 "1392",
"neyshaboor": 	 "10354",
"davarzan": 	 "60",
"mahvelat": 	 "592",
"kalat": 	 "203",
"jowayin": 	 "570",
"bardeskan": 	 "1668",
"zaveh": 	 "261",
"daregaz": 	 "1305",
"mashhad": 	 "140945",
"khaf": 	 "1604",
"taibad": 	 "1882",
"rashtkhar": 	 "377",
"binalud": 	 "1823",
"joghatay": 	 "460",
"khoshab": 	 "72",
"chenaran": 	 "1806",
"bakharz": 	 "367",
"firuzeh": 	 "82",
"sabzevar": 	 "8480",

"khorasan-southAVG": "2362",
"khorasan-southTotal": "25979",
"birjand": 	 "13346",
"boshrooyeh": 	 "813",
"qaenat": 	 "3439",
"tabas": 	 "1846",
"darmian": 	 "847",
"sarayan": 	 "831",
"": 	 "1231",
"sarbisheh": 	 "456",
"khoosf": 	 "218",
"ferdos": 	 "1958",
"nehbandan": 	 "994",

"khuzestanAVG": "4404",
"khuzestanTotal": "118911",
"ahvaz": 	 "47275",
"ramshir": 	 "843",
"izeh": 	 "2789",
"haftgol": 	 "359",
"dasht-e-azadegan": 	 "1344",
"omidieh": 	 "2049",
"aghajari": 	 "181",
"hamidieh": 	 "440",
"andimeshk": 	 "3343",
"khoramshahr": 	 "2637",
"bavi": 	 "638",
"gotvand": 	 "1027",
"lali": 	 "370",
"masjedsoleiman": 	 "2256",
"shoosh": 	 "3903",
"dezfool": 	 "12219",
"behbahan": 	 "6030",
"bandarmahshahr": 	 "6414",
"andika": 	 "24",
"shooshtar": 	 "4726",
"abadan": 	 "9111",
"baghmalek": 	 "915",
"ramhormoz": 	 "2581",
"hoveizeh": 	 "314",
"hendijan": 	 "700",
"": 	 "4630",
"shadegan": 	 "1793",

"kohgiluyeh-boyer-ahmadAVG": "2036",
"kohgiluyeh-boyer-ahmadTotal": "18324",
"bahmai": 	 "384",
"": 	 "1117",
"dana": 	 "431",
"choram": 	 "842",
"gachsaran": 	 "3234",
"boyer-ahmad": 	 "9177",
"kohgiluyeh": 	 "2609",
"lendeh": 	 "232",
"basht": 	 "298",

"kurdistanAVG": "4048",
"kurdistanTotal": "44532",
"dehgolan": 	 "1009",
"saghez": 	 "5466",
"marivan": 	 "5096",
"": 	 "1467",
"sarvabad": 	 "176",
"baneh": 	 "8696",
"sanandaj": 	 "14864",
"bijar": 	 "1689",
"kamyaran": 	 "1909",
"divandareh": 	 "1196",
"ghorveh": 	 "2964",

"lorestanAVG": "3413",
"lorestanTotal": "37543",
"boroojerd": 	 "7768",
"khoramabad": 	 "12161",
"poldokhtar": 	 "1361",
"dorood": 	 "3197",
"aligoodarz": 	 "3079",
"delfan": 	 "2099",
"dowreh": 	 "58",
"koohdasht": 	 "2590",
"": 	 "1839",
"azna": 	 "2227",
"selseleh": 	 "1164",

"markaziAVG": "3904",
"markaziTotal": "50749",
"shazand": 	 "1870",
"zarandieh": 	 "793",
"saveh": 	 "7272",
"khomein": 	 "3788",
"arak": 	 "28361",
"mahallat": 	 "2248",
"tafresh": 	 "666",
"komijan": 	 "990",
"ashtian": 	 "460",
"farahan": 	 "369",
"khandab": 	 "529",
"": 	 "1526",
"delijan": 	 "1877",

"mazandaranAVG": "5521",
"mazandaranTotal": "115948",
"chaloos": 	 "6784",
"abbasabad": 	 "2941",
"noshahr": 	 "5349",
"babol": 	 "16142",
"behshahr": 	 "4654",
"kelardasht": 	 "733",
"ghaemshahr": 	 "9732",
"amol": 	 "12347",
"neka": 	 "3063",
"mahmoodabad": 	 "3142",
"miandorud": 	 "214",
"jooybar": 	 "1286",
"noor": 	 "5288",
"ramsar": 	 "3564",
"babolsar": 	 "5247",
"sari": 	 "19491",
"savadkuh": 	 "1148",
"galoogah": 	 "633",
"fereidoonkenar": 	 "2678",
"": 	 "4154",
"tonekabon": 	 "7358",

"qazvinAVG": "6004",
"qazvinTotal": "42030",
"booeenzahra": 	 "2805",
"avaj": 	 "231",
"takestan": 	 "4386",
"qazvin": 	 "24980",
"": 	 "1493",
"alborz": 	 "4985",
"abeyek": 	 "3150",

"qomAVG": "21100",
"qomTotal": "42201",
"": 	 "1609",
"qom": 	 "40592",

"semnanAVG": "3524",
"semnanTotal": "31713",
"garmsar": 	 "3501",
"semnan": 	 "10211",
"mehdishahr": 	 "1660",
"aradan": 	 "285",
"damghan": 	 "3732",
"": 	 "1141",
"sorkheh": 	 "353",
"shahrood": 	 "10346",
"miamey": 	 "484",

"sistan-baluchestanAVG": "1969",
"sistan-baluchestanTotal": "39381",
"zahak": 	 "308",
"zabol": 	 "3947",
"iranshahr": 	 "4659",
"chabahar": 	 "4928",
"saravan": 	 "2586",
"konarak": 	 "703",
"fanooj": 	 "157",
"zahedan": 	 "16687",
"dalgan": 	 "88",
"hamun": 	 "26",
"": 	 "1254",
"khash": 	 "1709",
"ghasreghand": 	 "121",
"mehrestan": 	 "126",
"sarbaz": 	 "460",
"nimruz": 	 "13",
"mirjaveh": 	 "162",
"nikshahr": 	 "971",
"hirmand": 	 "60",
"sib-va-suran": 	 "416",

"tehranAVG": "46607",
"tehranTotal": "792323",
"ghods": 	 "7243",
"": 	 "16184",
"firoozkooh": 	 "1229",
"rey": 	 "15636",
"shahryar": 	 "18998",
"varamin": 	 "8160",
"robatkarim": 	 "6937",
"baharestan": 	 "8567",
"tehran": 	 "654742",
"pardis": 	 "2301",
"damavand": 	 "5201",
"gharchak": 	 "4971",
"eslamshahr": 	 "22502",
"pishva": 	 "1457",
"pakdasht": 	 "8494",
"shemiranat": 	 "1627",
"malard": 	 "8074",

"yazdAVG": "4865",
"yazdTotal": "53513",
"meibod": 	 "3457",
"ashkezar": 	 "782",
"yazd": 	 "37944",
"taft": 	 "1188",
"mehriz": 	 "1761",
"khatam": 	 "872",
"": 	 "1470",
"behabad": 	 "218",
"abarkooh": 	 "1545",
"ardakan": 	 "2965",
"bafgh": 	 "1311",

"zanjanAVG": "4026",
"zanjanTotal": "36236",
"zanjan": 	 "22905",
"abhar": 	 "6401",
"soltanieh": 	 "334",
"tarom": 	 "592",
"": 	 "1163",
"ijrud": 	 "123",
"mahneshan": 	 "392",
"khoramdareh": 	 "2038",
"khodabandeh": 	 "2288"
}
