{
"Dict": "Dict1",
"Date": "1394/11/30",
"AVG": "1069723",
"Total": "33161401",
"Quantity_Type": "تعداد تراکنش",
"alborz": 	 "134416",
"ardabil": 	 "87571",
"azerbaijan-east": 	 "279021",
"azerbaijan-west": 	 "178929",
"bushehr": 	 "67112",
"chahar-mahaal-bakhtiari": 	 "60973",
"fars": 	 "363939",
"gilan": 	 "626664",
"golestan": 	 "55248",
"hamadan": 	 "71134",
"hormozgan": 	 "247269",
"ilam": 	 "19601",
"isfahan": 	 "679129",
"kerman": 	 "184940",
"kermanshah": 	 "177263",
"khorasan-north": 	 "19515",
"khorasan-razavi": 	 "549345",
"khorasan-south": 	 "69444",
"khuzestan": 	 "396200",
"kohgiluyeh-boyer-ahmad": 	 "37839",
"kurdistan": 	 "85770",
"lorestan": 	 "112767",
"markazi": 	 "100248",
"mazandaran": 	 "285621",
"qazvin": 	 "273980",
"qom": 	 "120617",
"semnan": 	 "102931",
"sistan-baluchestan": 	 "45024",
"tehran": 	 "27543144",
"yazd": 	 "133579",
"zanjan": 	 "52168"
}
