{
"Dict": "Dict1",
"Date": "1395/07/30",
"AVG": "32656312",
"Total": "1012345670",
"Quantity_Type": "تعداد تراکنش",
"alborz": 	 "36352949",
"ardabil": 	 "8605809",
"azerbaijan-east": 	 "26648975",
"azerbaijan-west": 	 "20324623",
"bushehr": 	 "16115377",
"chahar-mahaal-bakhtiari": 	 "9750595",
"fars": 	 "63240275",
"gilan": 	 "19639918",
"golestan": 	 "14847477",
"hamadan": 	 "13899590",
"hormozgan": 	 "27893416",
"ilam": 	 "5396451",
"isfahan": 	 "65614888",
"kerman": 	 "38501716",
"kermanshah": 	 "12455535",
"khorasan-north": 	 "6392330",
"khorasan-razavi": 	 "67561015",
"khorasan-south": 	 "7306608",
"khuzestan": 	 "44515808",
"kohgiluyeh-boyer-ahmad": 	 "8129632",
"kurdistan": 	 "11837618",
"lorestan": 	 "11384523",
"markazi": 	 "13437547",
"mazandaran": 	 "30774042",
"qazvin": 	 "12530337",
"qom": 	 "13339959",
"semnan": 	 "7919166",
"sistan-baluchestan": 	 "18650484",
"tehran": 	 "352897919",
"yazd": 	 "17553232",
"zanjan": 	 "8827856"
}
