{
"Dict": "Dict1",
"Date": "1395/06/31",
"Quantity_Type": "تعداد پایانه دارای تراکنش",

"alborzAVG": "25589",
"alborzTotal": "179123",
"fardis": 	 "1190",
"eshtehard": 	 "3014",
"taleghan": 	 "638",
"karaj": 	 "156614",
"savojbolagh": 	 "8899",
"": 	 "2102",
"nazarabad": 	 "6666",

"ardabilAVG": "6133",
"ardabilTotal": "67459",
"nayer": 	 "685",
"sarein": 	 "1437",
"khalkhal": 	 "4499",
"ardebil": 	 "40607",
"parsabad": 	 "7873",
"kowsar": 	 "691",
"namin": 	 "1337",
"germi": 	 "2470",
"": 	 "355",
"meshginshahr": 	 "5732",
"bilesavar": 	 "1773",

"azerbaijan-eastAVG": "9702",
"azerbaijan-eastTotal": "213449",
"varzaghan": 	 "734",
"tabriz": 	 "125323",
"kaleibar": 	 "1655",
"oskoo": 	 "4386",
"ajabshir": 	 "2454",
"shabestar": 	 "6875",
"horand": 	 "243",
"ahar": 	 "5206",
"bonab": 	 "7520",
"": 	 "878",
"charuymaq": 	 "513",
"haris": 	 "1713",
"khoda-afarin": 	 "278",
"sarab": 	 "4924",
"malekan": 	 "3555",
"maragheh": 	 "12369",
"azarshahr": 	 "5499",
"hashtrood": 	 "2052",
"marand": 	 "12134",
"mianeh": 	 "7119",
"jolfa": 	 "4852",
"bostanabad": 	 "3167",

"azerbaijan-westAVG": "9023",
"azerbaijan-westTotal": "162414",
"bookan": 	 "11698",
"sardasht": 	 "5135",
"khoy": 	 "16468",
"chaypareh": 	 "2193",
"poldasht": 	 "1197",
"mahabad": 	 "13671",
"salmas": 	 "8504",
"piranshahr": 	 "7427",
"oshnavieh": 	 "2736",
"shahindezh": 	 "3247",
"naghadeh": 	 "6690",
"": 	 "383",
"makoo": 	 "5647",
"miandoab": 	 "10116",
"chaldoran": 	 "874",
"takab": 	 "3033",
"urumieh": 	 "61463",
"shoot": 	 "1932",

"bushehrAVG": "6487",
"bushehrTotal": "71358",
"dashti": 	 "3456",
"kangan": 	 "6664",
"jam": 	 "2703",
"asaloyeh": 	 "2693",
"": 	 "248",
"deyr": 	 "2842",
"tangestan": 	 "2390",
"deylam": 	 "3068",
"dashtestan": 	 "12483",
"boshehr": 	 "24987",
"ganaveh": 	 "9824",

"chahar-mahaal-bakhtiariAVG": "5702",
"chahar-mahaal-bakhtiariTotal": "57025",
"ardal": 	 "1296",
"": 	 "304",
"bon": 	 "996",
"boroojen": 	 "9726",
"farsan": 	 "5515",
"lordegan": 	 "6416",
"saman": 	 "2433",
"kuhrang": 	 "374",
"kiar": 	 "1888",
"shahrekord": 	 "28077",

"farsAVG": "8943",
"farsTotal": "268285",
"arsanjan": 	 "2037",
"lamerd": 	 "6420",
"jahrom": 	 "11669",
"mamasani": 	 "4829",
"khonj": 	 "1786",
"neyriz": 	 "4495",
"abadeh": 	 "6414",
"khorrambid": 	 "2658",
"marvdasht": 	 "17428",
"sepidan": 	 "2681",
"fasa": 	 "8016",
"firoozabad": 	 "5290",
"kovar": 	 "3402",
"larestan": 	 "10639",
"rostam": 	 "541",
"eghlid": 	 "4489",
"zarrin-dasht": 	 "1486",
"shiraz": 	 "133358",
"estahban": 	 "2672",
"qir-va-karzin": 	 "2442",
"gerash": 	 "2465",
"darab": 	 "8301",
"khorameh": 	 "1847",
"bovanat": 	 "1561",
"farashband": 	 "2159",
"": 	 "1073",
"kazeroon": 	 "13393",
"mehr": 	 "2468",
"pasargad": 	 "1295",
"sarvestan": 	 "971",

"gilanAVG": "8928",
"gilanTotal": "151784",
"somesara": 	 "5846",
"roodbar": 	 "4919",
"rezvanshahr": 	 "3244",
"rasht": 	 "61647",
"amlash": 	 "1811",
"shaft": 	 "1618",
"": 	 "828",
"lahijan": 	 "11864",
"siahkal": 	 "2239",
"rodsar": 	 "8396",
"bandaranzali": 	 "11350",
"talesh": 	 "7684",
"fooman": 	 "4070",
"masal": 	 "2659",
"langerood": 	 "8821",
"astanehashrafieh": 	 "6248",
"astara": 	 "8540",

"golestanAVG": "6933",
"golestanTotal": "103998",
"maraveh-tappeh": 	 "806",
"aliabad": 	 "7555",
"gomishan": 	 "1251",
"azadshahr": 	 "6658",
"galikesh": 	 "2149",
"": 	 "339",
"bandargaz": 	 "2796",
"torkaman": 	 "5143",
"gonbadkavoos": 	 "18308",
"minoodasht": 	 "4257",
"kolaleh": 	 "5141",
"ramyan": 	 "2484",
"aghghola": 	 "5684",
"gorgan": 	 "37338",
"kordkooy": 	 "4089",

"hamadanAVG": "9046",
"hamadanTotal": "90455",
"razan": 	 "3990",
"nahavand": 	 "6819",
"hamedan": 	 "46305",
"famenin": 	 "2500",
"": 	 "295",
"kabodarahang": 	 "4844",
"malayer": 	 "12713",
"bahar": 	 "4844",
"asadabad": 	 "4357",
"tooyserkan": 	 "3788",

"hormozganAVG": "8011",
"hormozganTotal": "112151",
"bandarabas": 	 "45580",
"bastak": 	 "4445",
"aboomoosa": 	 "54",
"minab": 	 "10087",
"gheshm": 	 "20236",
"sirik": 	 "1466",
"parsian": 	 "2872",
"bandarlengeh": 	 "18720",
"khomeyr": 	 "2151",
"jask": 	 "1286",
"rudan": 	 "2442",
"hajiabad": 	 "2142",
"bashagard": 	 "346",
"": 	 "324",

"ilamAVG": "3105",
"ilamTotal": "31048",
"darrehshahr": 	 "2516",
"ivan": 	 "2110",
"badreh": 	 "635",
"dehloran": 	 "2716",
"ilam": 	 "17349",
"": 	 "117",
"mehran": 	 "1128",
"malekshahi": 	 "531",
"abdanan": 	 "1994",
"chardavol": 	 "1952",

"isfahanAVG": "14653",
"isfahanTotal": "351669",
"golpayegan": 	 "7642",
"lenjan": 	 "14453",
"": 	 "860",
"samirom": 	 "3264",
"khansar": 	 "1984",
"khomeinishahr": 	 "15983",
"dehaghan": 	 "1379",
"falavarjan": 	 "11900",
"isfahan": 	 "187943",
"mobarakeh": 	 "8504",
"fereidoonshahr": 	 "1611",
"shahin-shahr-va-meymeh": 	 "12877",
"faridan": 	 "3122",
"ardestan": 	 "2659",
"natanz": 	 "2893",
"shahreza": 	 "13003",
"kashan": 	 "24094",
"chadegan": 	 "1284",
"najafabad": 	 "20723",
"khur-va-biabanak": 	 "902",
"borkhar": 	 "4991",
"naeen": 	 "2305",
"tiran-va-karvan": 	 "3060",
"aranbidgol": 	 "4233",

"kermanAVG": "6540",
"kermanTotal": "156956",
"fahraj": 	 "536",
"orzooeeyeh": 	 "649",
"manoojan": 	 "1376",
"ravar": 	 "1575",
"koohbanan": 	 "987",
"kerman": 	 "65196",
"rabor": 	 "1096",
"faryab": 	 "478",
"rigan": 	 "716",
"kahnooj": 	 "4037",
"jiroft": 	 "8762",
"zarand": 	 "7231",
"": 	 "212",
"rudbar-e-jonub": 	 "1471",
"rafsanjan": 	 "20533",
"baft": 	 "3152",
"narmashir": 	 "778",
"anar": 	 "1943",
"shahrebabak": 	 "4719",
"ghaleganj": 	 "1157",
"bam": 	 "8428",
"bardsir": 	 "2642",
"anbarabad": 	 "1501",
"sirjan": 	 "17781",

"kermanshahAVG": "5733",
"kermanshahTotal": "85989",
"sahneh": 	 "2186",
"kermanshah": 	 "53210",
"sarpolzahab": 	 "3428",
"salas-e-babajani": 	 "590",
"dalahu": 	 "514",
"songhor": 	 "2888",
"ravansar": 	 "2019",
"kangavar": 	 "3257",
"paveh": 	 "3687",
"hersin": 	 "2004",
"ghasreshirin": 	 "828",
"gilangharb": 	 "1470",
"eslamabadgharb": 	 "4606",
"javanrood": 	 "4943",
"": 	 "359",

"khorasan-northAVG": "5055",
"khorasan-northTotal": "40440",
"bojnoord": 	 "20353",
"garmeh": 	 "1211",
"maneh-va-samalqan": 	 "3108",
"jajarm": 	 "1743",
"shirvan": 	 "6469",
"farooj": 	 "1485",
"": 	 "319",
"esfarayen": 	 "5752",

"khorasan-razaviAVG": "12141",
"khorasan-razaviTotal": "352084",
"mahvelat": 	 "1694",
"kalat": 	 "861",
"bardeskan": 	 "3195",
"jowayin": 	 "1213",
"zaveh": 	 "839",
"chenaran": 	 "4258",
"bakharz": 	 "931",
"firuzeh": 	 "375",
"sabzevar": 	 "18960",
"ghoochan": 	 "6595",
"gonabad": 	 "5939",
"khalilabad": 	 "1861",
"fariman": 	 "2860",
"kashmar": 	 "8207",
"": 	 "984",
"torbatheydariyeh": 	 "12207",
"bejestan": 	 "1295",
"torbatjam": 	 "7335",
"sarakhs": 	 "2712",
"neyshaboor": 	 "19854",
"davarzan": 	 "300",
"daregaz": 	 "2320",
"mashhad": 	 "232677",
"khaf": 	 "4114",
"taibad": 	 "3853",
"rashtkhar": 	 "1085",
"binalud": 	 "4072",
"joghatay": 	 "1205",
"khoshab": 	 "283",

"khorasan-southAVG": "3966",
"khorasan-southTotal": "43625",
"khoosf": 	 "498",
"ferdos": 	 "3155",
"nehbandan": 	 "1854",
"birjand": 	 "22408",
"boshrooyeh": 	 "1249",
"qaenat": 	 "6258",
"tabas": 	 "3932",
"darmian": 	 "1479",
"sarayan": 	 "1597",
"": 	 "374",
"sarbisheh": 	 "821",

"khuzestanAVG": "8083",
"khuzestanTotal": "218233",
"shoosh": 	 "7945",
"dezfool": 	 "24035",
"behbahan": 	 "11990",
"": 	 "1023",
"shadegan": 	 "3588",
"ahvaz": 	 "81895",
"ramshir": 	 "1769",
"izeh": 	 "6126",
"haftgol": 	 "663",
"dasht-e-azadegan": 	 "2581",
"omidieh": 	 "4113",
"aghajari": 	 "371",
"hamidieh": 	 "1241",
"andimeshk": 	 "6940",
"khoramshahr": 	 "5658",
"bavi": 	 "1509",
"gotvand": 	 "1922",
"lali": 	 "872",
"masjedsoleiman": 	 "3963",
"bandarmahshahr": 	 "14334",
"andika": 	 "90",
"shooshtar": 	 "9169",
"abadan": 	 "16368",
"ramhormoz": 	 "4957",
"baghmalek": 	 "2214",
"hoveizeh": 	 "729",
"hendijan": 	 "2168",

"kohgiluyeh-boyer-ahmadAVG": "3980",
"kohgiluyeh-boyer-ahmadTotal": "35816",
"choram": 	 "1386",
"gachsaran": 	 "6436",
"lendeh": 	 "716",
"basht": 	 "663",
"bahmai": 	 "949",
"": 	 "237",
"dana": 	 "825",
"kohgiluyeh": 	 "5396",
"boyer-ahmad": 	 "19208",

"kurdistanAVG": "7843",
"kurdistanTotal": "86270",
"kamyaran": 	 "4503",
"dehgolan": 	 "2533",
"marivan": 	 "9369",
"saghez": 	 "11456",
"": 	 "199",
"sarvabad": 	 "648",
"baneh": 	 "15294",
"bijar": 	 "3462",
"sanandaj": 	 "29412",
"divandareh": 	 "2675",
"ghorveh": 	 "6719",

"lorestanAVG": "6459",
"lorestanTotal": "71049",
"aligoodarz": 	 "5918",
"delfan": 	 "3874",
"": 	 "226",
"azna": 	 "3540",
"selseleh": 	 "2381",
"boroojerd": 	 "14938",
"khoramabad": 	 "25085",
"poldokhtar": 	 "2792",
"dorood": 	 "6590",
"dowreh": 	 "320",
"koohdasht": 	 "5385",

"markaziAVG": "6318",
"markaziTotal": "82136",
"farahan": 	 "664",
"delijan": 	 "3412",
"shazand": 	 "3532",
"zarandieh": 	 "2067",
"saveh": 	 "13112",
"khomein": 	 "5957",
"arak": 	 "43798",
"mahallat": 	 "3910",
"tafresh": 	 "1251",
"komijan": 	 "1925",
"ashtian": 	 "776",
"khandab": 	 "1452",
"": 	 "280",

"mazandaranAVG": "10564",
"mazandaranTotal": "221840",
"ghaemshahr": 	 "19209",
"amol": 	 "25822",
"neka": 	 "5983",
"galoogah": 	 "1440",
"fereidoonkenar": 	 "5190",
"": 	 "1276",
"tonekabon": 	 "13213",
"chaloos": 	 "12556",
"abbasabad": 	 "5982",
"noshahr": 	 "10037",
"behshahr": 	 "8852",
"babol": 	 "31719",
"kelardasht": 	 "1634",
"mahmoodabad": 	 "6842",
"miandorud": 	 "797",
"jooybar": 	 "3396",
"noor": 	 "10708",
"ramsar": 	 "7090",
"babolsar": 	 "10797",
"sari": 	 "36646",
"savadkuh": 	 "2651",

"qazvinAVG": "10656",
"qazvinTotal": "74589",
"": 	 "315",
"alborz": 	 "10509",
"abeyek": 	 "5588",
"booeenzahra": 	 "5649",
"avaj": 	 "772",
"takestan": 	 "8261",
"qazvin": 	 "43495",

"qomAVG": "35412",
"qomTotal": "70825",
"qom": 	 "70567",
"": 	 "258",

"semnanAVG": "5606",
"semnanTotal": "50458",
"shahrood": 	 "17360",
"miamey": 	 "1071",
"garmsar": 	 "6072",
"semnan": 	 "15595",
"mehdishahr": 	 "2449",
"aradan": 	 "554",
"damghan": 	 "6572",
"": 	 "123",
"sorkheh": 	 "662",

"sistan-baluchestanAVG": "3887",
"sistan-baluchestanTotal": "77745",
"khash": 	 "3620",
"ghasreghand": 	 "454",
"nikshahr": 	 "2132",
"sib-va-suran": 	 "1224",
"hirmand": 	 "301",
"zahak": 	 "828",
"zabol": 	 "7213",
"iranshahr": 	 "8628",
"chabahar": 	 "9127",
"saravan": 	 "5627",
"konarak": 	 "1899",
"fanooj": 	 "525",
"zahedan": 	 "32005",
"dalgan": 	 "484",
"hamun": 	 "120",
"": 	 "745",
"mehrestan": 	 "433",
"sarbaz": 	 "1832",
"nimruz": 	 "50",
"mirjaveh": 	 "498",

"tehranAVG": "63307",
"tehranTotal": "1076220",
"pakdasht": 	 "15840",
"shemiranat": 	 "2813",
"malard": 	 "14459",
"ghods": 	 "14388",
"": 	 "5322",
"firoozkooh": 	 "2164",
"rey": 	 "27784",
"shahryar": 	 "32527",
"varamin": 	 "13596",
"robatkarim": 	 "12318",
"baharestan": 	 "19102",
"tehran": 	 "855083",
"pardis": 	 "4309",
"damavand": 	 "8175",
"gharchak": 	 "8646",
"eslamshahr": 	 "36905",
"pishva": 	 "2789",

"yazdAVG": "8632",
"yazdTotal": "94949",
"khatam": 	 "1943",
"ardakan": 	 "5728",
"bafgh": 	 "2595",
"meibod": 	 "6945",
"ashkezar": 	 "1749",
"yazd": 	 "64752",
"taft": 	 "2618",
"mehriz": 	 "3808",
"": 	 "303",
"behabad": 	 "710",
"abarkooh": 	 "3798",

"zanjanAVG": "6692",
"zanjanTotal": "60231",
"ijrud": 	 "442",
"khoramdareh": 	 "4128",
"khodabandeh": 	 "4963",
"zanjan": 	 "36766",
"abhar": 	 "10695",
"soltanieh": 	 "800",
"tarom": 	 "1237",
"": 	 "329",
"mahneshan": 	 "871"
}
