{
"Dict": "Dict1",
"Date": "1396/09/30",
"AVG": "185050",
"Total": "5736535",
"Quantity_Type": "تعداد پایانه دارای تراکنش",
"alborz": 	 "207893",
"ardabil": 	 "82383",
"azerbaijan-east": 	 "256193",
"azerbaijan-west": 	 "198511",
"bushehr": 	 "91501",
"chahar-mahaal-bakhtiari": 	 "70025",
"fars": 	 "330407",
"gilan": 	 "188960",
"golestan": 	 "125881",
"hamadan": 	 "104996",
"hormozgan": 	 "134132",
"ilam": 	 "40111",
"isfahan": 	 "414802",
"kerman": 	 "188833",
"kermanshah": 	 "105628",
"khorasan-north": 	 "53232",
"khorasan-razavi": 	 "437443",
"khorasan-south": 	 "54093",
"khuzestan": 	 "275466",
"kohgiluyeh-boyer-ahmad": 	 "43833",
"kurdistan": 	 "104739",
"lorestan": 	 "90247",
"markazi": 	 "97646",
"mazandaran": 	 "273676",
"qazvin": 	 "87712",
"qom": 	 "83711",
"semnan": 	 "59926",
"sistan-baluchestan": 	 "104530",
"tehran": 	 "1244852",
"yazd": 	 "113763",
"zanjan": 	 "71410"
}
