{
"Dict": "Dict1",
"Date": "1397/12/29",
"AVG": "63735542",
"Total": "1975801806",
"Quantity_Type": "تعداد تراکنش",
"alborz": 	 "78588037",
"ardabil": 	 "21762768",
"azerbaijan-east": 	 "65734812",
"azerbaijan-west": 	 "50893311",
"bushehr": 	 "36024200",
"chahar-mahaal-bakhtiari": 	 "21766857",
"fars": 	 "145575096",
"gilan": 	 "46205015",
"golestan": 	 "34856021",
"hamadan": 	 "34167635",
"hormozgan": 	 "59754438",
"ilam": 	 "13416993",
"isfahan": 	 "142468097",
"kerman": 	 "83796125",
"kermanshah": 	 "32771244",
"khorasan-north": 	 "16622298",
"khorasan-razavi": 	 "151561459",
"khorasan-south": 	 "16641611",
"khuzestan": 	 "116509789",
"kohgiluyeh-boyer-ahmad": 	 "18392534",
"kurdistan": 	 "27792113",
"lorestan": 	 "31480302",
"markazi": 	 "32962912",
"mazandaran": 	 "74437093",
"qazvin": 	 "31201452",
"qom": 	 "31613262",
"semnan": 	 "17908843",
"sistan-baluchestan": 	 "49293839",
"tehran": 	 "435205637",
"yazd": 	 "35327171",
"zanjan": 	 "21070842"
}
