{
"Dict": "Dict1",
"Date": "1398/09/30",
"Quantity_Type": "تعداد تراکنش",

"alborzAVG": "219",
"alborzTotal": "657",
"karaj": 	 "653" ,
"savojbolagh": 	 "1" ,
"nazarabad": 	 "3" ,

"ardabilAVG": "4",
"ardabilTotal": "18",
"ardebil": 	 "13" ,
"parsabad": 	 "2" ,
"germi": 	 "1" ,
"sarein": 	 "1" ,
"meshginshahr": 	 "1" ,

"azerbaijan-eastAVG": "58",
"azerbaijan-eastTotal": "407",
"oskoo": 	 "14" ,
"bonab": 	 "2" ,
"varzaghan": 	 "7" ,
"tabriz": 	 "337" ,
"mianeh": 	 "31" ,
"jolfa": 	 "2" ,
"bostanabad": 	 "14" ,

"azerbaijan-westAVG": "21",
"azerbaijan-westTotal": "185",
"khoy": 	 "1" ,
"salmas": 	 "1" ,
"shahindezh": 	 "1" ,
"naghadeh": 	 "8" ,
"bookan": 	 "25" ,
"sardasht": 	 "1" ,
"makoo": 	 "1" ,
"takab": 	 "1" ,
"urumieh": 	 "146" ,

"bushehrAVG": "21",
"bushehrTotal": "170",
"kangan": 	 "33" ,
"jam": 	 "29" ,
"asaloyeh": 	 "7" ,
"deyr": 	 "1" ,
"tangestan": 	 "7" ,
"dashti": 	 "3" ,
"boshehr": 	 "79" ,
"ganaveh": 	 "11" ,

"chahar-mahaal-bakhtiariAVG": "614",
"chahar-mahaal-bakhtiariTotal": "1229",
"farsan": 	 "1221" ,
"shahrekord": 	 "8" ,

"farsAVG": "108",
"farsTotal": "1506",
"khonj": 	 "1" ,
"abadeh": 	 "3" ,
"neyriz": 	 "1" ,
"sepidan": 	 "1" ,
"firoozabad": 	 "2" ,
"larestan": 	 "2" ,
"eghlid": 	 "2" ,
"shiraz": 	 "1288" ,
"lamerd": 	 "175" ,
"estahban": 	 "11" ,
"gerash": 	 "5" ,
"farashband": 	 "7" ,
"kazeroon": 	 "1" ,
"mehr": 	 "7" ,

"gilanAVG": "105",
"gilanTotal": "524",
"rasht": 	 "519" ,
"roodbar": 	 "2" ,
"rezvanshahr": 	 "1" ,
"astanehashrafieh": 	 "1" ,
"astara": 	 "1" ,

"golestanAVG": "87",
"golestanTotal": "433",
"galikesh": 	 "2" ,
"gonbadkavoos": 	 "202" ,
"minoodasht": 	 "1" ,
"aliabad": 	 "2" ,
"gorgan": 	 "226" ,

"hamadanAVG": "91",
"hamadanTotal": "546",
"hamedan": 	 "505" ,
"famenin": 	 "2" ,
"kabodarahang": 	 "11" ,
"malayer": 	 "1" ,
"bahar": 	 "16" ,
"nahavand": 	 "11" ,

"hormozganAVG": "511440",
"hormozganTotal": "3068637",
"minab": 	 "5" ,
"gheshm": 	 "10" ,
"bandarlengeh": 	 "250735" ,
"rudan": 	 "20" ,
"bandarabas": 	 "12020" ,
"": 	 "2805847" ,

"ilamAVG": "449",
"ilamTotal": "898",
"ilam": 	 "180" ,
"chardavol": 	 "718" ,

"isfahanAVG": "443",
"isfahanTotal": "3984",
"samirom": 	 "2" ,
"khomeinishahr": 	 "5" ,
"isfahan": 	 "3935" ,
"mobarakeh": 	 "18" ,
"shahin-shahr-va-meymeh": 	 "3" ,
"kashan": 	 "12" ,
"lenjan": 	 "6" ,
"khur-va-biabanak": 	 "2" ,
"borkhar": 	 "1" ,

"kermanAVG": "200",
"kermanTotal": "2203",
"manoojan": 	 "1" ,
"koohbanan": 	 "86" ,
"kerman": 	 "1908" ,
"kahnooj": 	 "1" ,
"jiroft": 	 "1" ,
"zarand": 	 "12" ,
"baft": 	 "17" ,
"narmashir": 	 "3" ,
"shahrebabak": 	 "19" ,
"bam": 	 "51" ,
"sirjan": 	 "104" ,

"kermanshahAVG": "1135",
"kermanshahTotal": "3404",
"kermanshah": 	 "3394" ,
"salas-e-babajani": 	 "8" ,
"eslamabadgharb": 	 "2" ,

"khorasan-northAVG": "39",
"khorasan-northTotal": "157",
"garmeh": 	 "54" ,
"shirvan": 	 "22" ,
"bojnoord": 	 "28" ,
"esfarayen": 	 "53" ,

"khorasan-razaviAVG": "1173",
"khorasan-razaviTotal": "15253",
"sabzevar": 	 "48" ,
"gonabad": 	 "11" ,
"kashmar": 	 "10944" ,
"torbatheydariyeh": 	 "256" ,
"bejestan": 	 "1" ,
"torbatjam": 	 "3" ,
"neyshaboor": 	 "378" ,
"mahvelat": 	 "8" ,
"bardeskan": 	 "7" ,
"mashhad": 	 "3576" ,
"khaf": 	 "9" ,
"taibad": 	 "2" ,
"binalud": 	 "10" ,

"khorasan-southAVG": "8",
"khorasan-southTotal": "31",
"birjand": 	 "15" ,
"qaenat": 	 "3" ,
"tabas": 	 "11" ,
"": 	 "2" ,

"khuzestanAVG": "46",
"khuzestanTotal": "457",
"shadegan": 	 "1" ,
"ahvaz": 	 "339" ,
"izeh": 	 "1" ,
"shoosh": 	 "1" ,
"dezfool": 	 "5" ,
"behbahan": 	 "19" ,
"bandarmahshahr": 	 "1" ,
"shooshtar": 	 "77" ,
"abadan": 	 "3" ,
"ramhormoz": 	 "10" ,

"kohgiluyeh-boyer-ahmadAVG": "35",
"kohgiluyeh-boyer-ahmadTotal": "104",
"lendeh": 	 "18" ,
"gachsaran": 	 "9" ,
"boyer-ahmad": 	 "77" ,

"kurdistanAVG": "113",
"kurdistanTotal": "338",
"baneh": 	 "1" ,
"sanandaj": 	 "327" ,
"bijar": 	 "10" ,

"lorestanAVG": "336",
"lorestanTotal": "673",
"boroojerd": 	 "2" ,
"khoramabad": 	 "671" ,

"markaziAVG": "105",
"markaziTotal": "316",
"saveh": 	 "37" ,
"arak": 	 "277" ,
"farahan": 	 "2" ,

"mazandaranAVG": "89",
"mazandaranTotal": "622",
"tonekabon": 	 "4" ,
"noshahr": 	 "4" ,
"babol": 	 "17" ,
"ghaemshahr": 	 "3" ,
"amol": 	 "3" ,
"babolsar": 	 "1" ,
"sari": 	 "590" ,

"qazvinAVG": "204",
"qazvinTotal": "204",
"qazvin": 	 "204" ,

"qomAVG": "5026",
"qomTotal": "5026",
"qom": 	 "5026" ,

"semnanAVG": "13",
"semnanTotal": "64",
"shahrood": 	 "33" ,
"garmsar": 	 "2" ,
"semnan": 	 "27" ,
"mehdishahr": 	 "1" ,
"damghan": 	 "1" ,

"sistan-baluchestanAVG": "4",
"sistan-baluchestanTotal": "18",
"zabol": 	 "1" ,
"iranshahr": 	 "8" ,
"chabahar": 	 "1" ,
"saravan": 	 "2" ,
"zahedan": 	 "6" ,

"tehranAVG": "11147201",
"tehranTotal": "122619214",
"pakdasht": 	 "10" ,
"shemiranat": 	 "97" ,
"ghods": 	 "2" ,
"": 	 "680" ,
"rey": 	 "350" ,
"shahryar": 	 "4" ,
"baharestan": 	 "12" ,
"tehran": 	 "122617942" ,
"damavand": 	 "92" ,
"gharchak": 	 "3" ,
"eslamshahr": 	 "22" ,

"yazdAVG": "91",
"yazdTotal": "364",
"bafgh": 	 "1" ,
"meibod": 	 "11" ,
"yazd": 	 "350" ,
"taft": 	 "2" ,

"zanjanAVG": "1097",
"zanjanTotal": "6583",
"khoramdareh": 	 "6" ,
"khodabandeh": 	 "7" ,
"zanjan": 	 "6556" ,
"abhar": 	 "12" ,
"soltanieh": 	 "1" ,
"mahneshan": 	 "1" 
}
