{
"Dict": "Dict1",
"Date": "1398/03/31",
"Quantity_Type": "تعداد تراکنش",

"alborzAVG": "236",
"alborzTotal": "707",
"karaj": 	 "688" ,
"nazarabad": 	 "3" ,
"savojbolagh": 	 "16" ,

"ardabilAVG": "68",
"ardabilTotal": "136",
"ardebil": 	 "135" ,
"germi": 	 "1" ,

"azerbaijan-eastAVG": "107",
"azerbaijan-eastTotal": "853",
"oskoo": 	 "10" ,
"shabestar": 	 "1" ,
"ahar": 	 "2" ,
"sarab": 	 "1" ,
"tabriz": 	 "796" ,
"mianeh": 	 "31" ,
"jolfa": 	 "11" ,
"bostanabad": 	 "1" ,

"azerbaijan-westAVG": "50",
"azerbaijan-westTotal": "496",
"khoy": 	 "2" ,
"oshnavieh": 	 "3" ,
"shahindezh": 	 "1" ,
"naghadeh": 	 "87" ,
"salmas": 	 "4" ,
"bookan": 	 "40" ,
"makoo": 	 "2" ,
"miandoab": 	 "13" ,
"urumieh": 	 "343" ,
"shoot": 	 "1" ,

"bushehrAVG": "26",
"bushehrTotal": "210",
"kangan": 	 "3" ,
"tangestan": 	 "6" ,
"jam": 	 "8" ,
"asaloyeh": 	 "12" ,
"deyr": 	 "10" ,
"dashtestan": 	 "1" ,
"boshehr": 	 "157" ,
"ganaveh": 	 "13" ,

"chahar-mahaal-bakhtiariAVG": "964",
"chahar-mahaal-bakhtiariTotal": "2892",
"farsan": 	 "2872" ,
"lordegan": 	 "5" ,
"shahrekord": 	 "15" ,

"farsAVG": "204",
"farsTotal": "3665",
"khonj": 	 "12" ,
"abadeh": 	 "11" ,
"marvdasht": 	 "3" ,
"firoozabad": 	 "2" ,
"sepidan": 	 "10" ,
"fasa": 	 "26" ,
"larestan": 	 "4" ,
"eghlid": 	 "6" ,
"shiraz": 	 "2985" ,
"lamerd": 	 "564" ,
"jahrom": 	 "6" ,
"mamasani": 	 "1" ,
"estahban": 	 "9" ,
"gerash": 	 "14" ,
"farashband": 	 "5" ,
"kazeroon": 	 "5" ,
"mehr": 	 "1" ,
"sarvestan": 	 "1" ,

"gilanAVG": "750",
"gilanTotal": "4500",
"rasht": 	 "4400" ,
"amlash": 	 "1" ,
"bandaranzali": 	 "90" ,
"roodbar": 	 "7" ,
"fooman": 	 "1" ,
"astara": 	 "1" ,

"golestanAVG": "803",
"golestanTotal": "4816",
"gonbadkavoos": 	 "168" ,
"galikesh": 	 "2" ,
"minoodasht": 	 "1" ,
"kolaleh": 	 "3" ,
"aliabad": 	 "3" ,
"gorgan": 	 "4639" ,

"hamadanAVG": "391",
"hamadanTotal": "1956",
"hamedan": 	 "1932" ,
"bahar": 	 "17" ,
"razan": 	 "2" ,
"nahavand": 	 "4" ,
"asadabad": 	 "1" ,

"hormozganAVG": "402758",
"hormozganTotal": "3624821",
"bandarlengeh": 	 "235748" ,
"jask": 	 "2" ,
"rudan": 	 "26" ,
"minab": 	 "26" ,
"gheshm": 	 "16" ,
"parsian": 	 "31" ,
"bandarabas": 	 "11798" ,
"bastak": 	 "389" ,
"": 	 "3376785" ,

"ilamAVG": "164",
"ilamTotal": "984",
"dehloran": 	 "8" ,
"malekshahi": 	 "4" ,
"abdanan": 	 "2" ,
"ilam": 	 "438" ,
"mehran": 	 "13" ,
"chardavol": 	 "519" ,

"isfahanAVG": "445",
"isfahanTotal": "7122",
"samirom": 	 "1" ,
"khomeinishahr": 	 "8" ,
"mobarakeh": 	 "1" ,
"shahin-shahr-va-meymeh": 	 "58" ,
"ardestan": 	 "16" ,
"dehaghan": 	 "1" ,
"falavarjan": 	 "1" ,
"isfahan": 	 "6987" ,
"kashan": 	 "18" ,
"golpayegan": 	 "1" ,
"lenjan": 	 "5" ,
"chadegan": 	 "1" ,
"najafabad": 	 "7" ,
"khur-va-biabanak": 	 "10" ,
"borkhar": 	 "3" ,
"tiran-va-karvan": 	 "4" ,

"kermanAVG": "387",
"kermanTotal": "4640",
"manoojan": 	 "1" ,
"koohbanan": 	 "154" ,
"rafsanjan": 	 "21" ,
"kerman": 	 "4317" ,
"rabor": 	 "1" ,
"rigan": 	 "3" ,
"kahnooj": 	 "3" ,
"zarand": 	 "17" ,
"baft": 	 "13" ,
"shahrebabak": 	 "4" ,
"bam": 	 "50" ,
"sirjan": 	 "56" ,

"kermanshahAVG": "516",
"kermanshahTotal": "1548",
"kermanshah": 	 "1426" ,
"salas-e-babajani": 	 "120" ,
"eslamabadgharb": 	 "2" ,

"khorasan-northAVG": "27",
"khorasan-northTotal": "107",
"garmeh": 	 "43" ,
"shirvan": 	 "7" ,
"bojnoord": 	 "5" ,
"esfarayen": 	 "52" ,

"khorasan-razaviAVG": "2857",
"khorasan-razaviTotal": "34285",
"sabzevar": 	 "25" ,
"gonabad": 	 "15" ,
"fariman": 	 "1" ,
"torbatheydariyeh": 	 "364" ,
"torbatjam": 	 "18" ,
"neyshaboor": 	 "215" ,
"mahvelat": 	 "5" ,
"bardeskan": 	 "14" ,
"mashhad": 	 "33607" ,
"khaf": 	 "2" ,
"taibad": 	 "14" ,
"binalud": 	 "5" ,

"khorasan-southAVG": "14",
"khorasan-southTotal": "72",
"khoosf": 	 "1" ,
"birjand": 	 "41" ,
"boshrooyeh": 	 "6" ,
"qaenat": 	 "12" ,
"tabas": 	 "12" ,

"khuzestanAVG": "82",
"khuzestanTotal": "1060",
"ahvaz": 	 "1007" ,
"ramshir": 	 "1" ,
"izeh": 	 "1" ,
"dasht-e-azadegan": 	 "5" ,
"lali": 	 "6" ,
"masjedsoleiman": 	 "1" ,
"shoosh": 	 "6" ,
"dezfool": 	 "9" ,
"behbahan": 	 "4" ,
"bandarmahshahr": 	 "15" ,
"shooshtar": 	 "2" ,
"abadan": 	 "1" ,
"ramhormoz": 	 "2" ,

"kohgiluyeh-boyer-ahmadAVG": "82",
"kohgiluyeh-boyer-ahmadTotal": "245",
"lendeh": 	 "11" ,
"gachsaran": 	 "10" ,
"boyer-ahmad": 	 "224" ,

"kurdistanAVG": "171",
"kurdistanTotal": "1027",
"baneh": 	 "5" ,
"sanandaj": 	 "1000" ,
"bijar": 	 "13" ,
"marivan": 	 "7" ,
"saghez": 	 "1" ,
"kamyaran": 	 "1" ,

"lorestanAVG": "7",
"lorestanTotal": "22",
"khoramabad": 	 "10" ,
"dorood": 	 "11" ,
"koohdasht": 	 "1" ,

"markaziAVG": "77",
"markaziTotal": "463",
"khomein": 	 "2" ,
"arak": 	 "413" ,
"saveh": 	 "37" ,
"mahallat": 	 "2" ,
"komijan": 	 "3" ,
"farahan": 	 "6" ,

"mazandaranAVG": "186",
"mazandaranTotal": "1856",
"fereidoonkenar": 	 "1" ,
"tonekabon": 	 "1" ,
"noshahr": 	 "4" ,
"chaloos": 	 "2" ,
"abbasabad": 	 "5" ,
"babol": 	 "46" ,
"ghaemshahr": 	 "1" ,
"noor": 	 "1" ,
"babolsar": 	 "3" ,
"sari": 	 "1792" ,

"qazvinAVG": "312",
"qazvinTotal": "312",
"qazvin": 	 "312" ,

"qomAVG": "5956",
"qomTotal": "5956",
"qom": 	 "5956" ,

"semnanAVG": "10",
"semnanTotal": "42",
"shahrood": 	 "15" ,
"semnan": 	 "16" ,
"mehdishahr": 	 "5" ,
"damghan": 	 "6" ,

"sistan-baluchestanAVG": "6",
"sistan-baluchestanTotal": "32",
"saravan": 	 "8" ,
"zahedan": 	 "1" ,
"zabol": 	 "1" ,
"iranshahr": 	 "15" ,
"khash": 	 "7" ,

"tehranAVG": "10154850",
"tehranTotal": "132013055",
"pakdasht": 	 "27" ,
"shemiranat": 	 "82" ,
"malard": 	 "7" ,
"robatkarim": 	 "1" ,
"ghods": 	 "4" ,
"": 	 "1195" ,
"rey": 	 "91" ,
"shahryar": 	 "5" ,
"baharestan": 	 "8" ,
"tehran": 	 "132011620" ,
"pardis": 	 "1" ,
"gharchak": 	 "3" ,
"eslamshahr": 	 "11" ,

"yazdAVG": "251",
"yazdTotal": "752",
"yazd": 	 "701" ,
"mehriz": 	 "50" ,
"abarkooh": 	 "1" ,

"zanjanAVG": "960",
"zanjanTotal": "6720",
"khoramdareh": 	 "9" ,
"khodabandeh": 	 "1" ,
"zanjan": 	 "6691" ,
"abhar": 	 "7" ,
"soltanieh": 	 "1" ,
"tarom": 	 "10" ,
"mahneshan": 	 "1" 
}
